buildout.cfg
setup.py
src/zc/__init__.py
src/zc.sshtunnel.egg-info/PKG-INFO
src/zc.sshtunnel.egg-info/SOURCES.txt
src/zc.sshtunnel.egg-info/dependency_links.txt
src/zc.sshtunnel.egg-info/entry_points.txt
src/zc.sshtunnel.egg-info/namespace_packages.txt
src/zc.sshtunnel.egg-info/not-zip-safe
src/zc.sshtunnel.egg-info/requires.txt
src/zc.sshtunnel.egg-info/top_level.txt
src/zc/sshtunnel/README.txt
src/zc/sshtunnel/__init__.py
src/zc/sshtunnel/recipe.py
src/zc/sshtunnel/tests.py
