Metadata-Version: 1.0
Name: zc.sshtunnel
Version: 1.2
Summary: zc.buildout recipe to manage an SSH tunnel.
Home-page: UNKNOWN
Author: Zope Corporation and contributors
Author-email: zope3-dev@zope.org
License: ZPL 2.1
Platform: UNKNOWN
Classifier: Framework :: Buildout
Classifier: License :: OSI Approved :: Zope Public License
Classifier: Programming Language :: Python
